simplematch.py
simplematch-1.3.dist-info/LICENSE.txt
simplematch-1.3.dist-info/WHEEL
simplematch-1.3.dist-info/METADATA
simplematch-1.3.dist-info/RECORD
