Metadata-Version: 2.1
Name: simplematch
Version: 1.3
Summary: Minimal, super readable string pattern matching.
Home-page: https://github.com/tfeldmann/simplematch
License: MIT
Keywords: string,pattern,matching,regular,expression,regex
Author: Thomas Feldmann
Author-email: mail@tfeldmann.de
Requires-Python: >=3.6,<4.0
Classifier: Development Status :: 5 - Production/Stable
Classifier: License :: OSI Approved :: MIT License
Classifier: Operating System :: OS Independent
Classifier: Programming Language :: Python :: 3
Classifier: Programming Language :: Python :: 3.6
Classifier: Programming Language :: Python :: 3.7
Classifier: Programming Language :: Python :: 3.8
Classifier: Programming Language :: Python :: 3.9
Classifier: Topic :: Software Development :: Libraries
Classifier: Topic :: Text Processing
Classifier: Topic :: Utilities
Project-URL: Repository, https://github.com/tfeldmann/simplematch
